dictionary/__init__.py
dictionary/__main__.py
dictionary/app.py
dictionary/data.json
simple_dictionary-0.1.3.dist-info/LICENSE
simple_dictionary-0.1.3.dist-info/METADATA
simple_dictionary-0.1.3.dist-info/WHEEL
simple_dictionary-0.1.3.dist-info/entry_points.txt
simple_dictionary-0.1.3.dist-info/top_level.txt
simple_dictionary-0.1.3.dist-info/RECORD
