Metadata-Version: 2.1
Name: simple-dictionary
Version: 0.1.3
Summary: Read the definition of a word
Home-page: https://github.com/AlexiaArtemis/simpledictionary
Author: Alexia Artemis Baikas
Author-email: alexiabaikas4@gmail.com
License: MIT
Platform: UNKNOWN
Classifier: License :: OSI Approved :: MIT License
Classifier: Programming Language :: Python
Classifier: Programming Language :: Python :: 3
License-File: LICENSE
